Metadata-Version: 1.1
Name: metabolenv-flag
Version: 1.1.0
Summary: Get boolean values from environment variables.
Home-page: https://github.com/bodylabs/env-flag
Author: Body Labs
Author-email: paul.melnikow@bodylabs.com
License: MIT
Platform: UNKNOWN
Classifier: Development Status :: 3 - Alpha
Classifier: Intended Audience :: Developers
Classifier: License :: OSI Approved :: BSD License
Classifier: Operating System :: OS Independent
Classifier: Programming Language :: Python :: 2.7
Classifier: Programming Language :: Python :: 3
